ztk_api/__init__.py
ztk_api/auth_account_args.py
ztk_api/bang_dan_tui_jian_args.py
ztk_api/bang_dan_tui_jian_model.py
ztk_api/bang_dan_tui_jian_resp.py
ztk_api/base_args.py
ztk_api/batch_item_args.py
ztk_api/batch_item_model.py
ztk_api/batch_item_resp.py
ztk_api/channel_account_info_args.py
ztk_api/channel_id_list_args.py
ztk_api/channel_invite_code_args.py
ztk_api/channel_save_record_args.py
ztk_api/fields.py
ztk_api/gao_yong_args.py
ztk_api/gao_yong_model.py
ztk_api/gao_yong_resp.py
ztk_api/guess_you_like_args.py
ztk_api/guess_you_like_model.py
ztk_api/guess_you_like_resp.py
ztk_api/item_detail_args.py
ztk_api/item_detail_model.py
ztk_api/item_detail_resp.py
ztk_api/item_detail_v2_args.py
ztk_api/item_detail_v2_model.py
ztk_api/item_detail_v2_resp.py
ztk_api/ju_hua_suan_args.py
ztk_api/ju_hua_suan_model.py
ztk_api/ju_hua_suan_resp.py
ztk_api/keyword_args.py
ztk_api/new_order_args.py
ztk_api/nine_nine_args.py
ztk_api/nine_nine_model.py
ztk_api/nine_nine_resp.py
ztk_api/order_details_resp.py
ztk_api/search_args.py
ztk_api/search_model.py
ztk_api/search_resp.py
ztk_api/suggest_args.py
ztk_api/test_slot.py
ztk_api/tkl_create_args.py
ztk_api/tkl_create_resp.py
ztk_api/tmall_chao_shi_args.py
ztk_api/tmall_chao_shi_model.py
ztk_api/tmall_chao_shi_resp.py
ztk_api/tmall_shang_pin_args.py
ztk_api/tmall_shang_pin_model.py
ztk_api/tmall_shang_pin_resp.py
ztk_api/ztk.py
ztk_api/ztk_std.py
ztk_api/ztk_sync.py
ztk_api-0.3.3.dist-info/WHEEL
ztk_api-0.3.3.dist-info/METADATA
ztk_api-0.3.3.dist-info/RECORD
