Metadata-Version: 2.1
Name: ztk-api
Version: 0.3.3
Summary: 折淘客接口
Home-page: https://github.com/QiYuTechDev/ztk_api
Author: dev
Author-email: dev@qiyutech.tech
Requires-Python: >=3.9,<4.0
Classifier: Programming Language :: Python :: 3
Classifier: Programming Language :: Python :: 3.9
Requires-Dist: aiohttp (>=3.7,<4)
Requires-Dist: dataclasses-json (>=0.5,<0.6)
Requires-Dist: pydantic (>=1.7,<2)
Requires-Dist: requests (>=2.25,<3)
Requires-Dist: structlog (>=21,<22)
Requires-Dist: tbk_api (>=0.2.1,<0.3)
